[  
    {
        "id": "NK001",
        "brand": "TOMMY HILFIGER KIDS",
        "name": "로고 패디드 자켓",
        "price": "199,750",
        "regular": "235,000",
        "percent": "15%",
        "img": "img/NewIn/Kids/001.jpg",
        "imgSub1":"img/NewIn/Kids/002-1.jpg",
        "category": "키즈",
        "gender":"공용",
        "style":"아우터"
    },
    {
        "id": "NK002",
        "brand": "TOMMY HILFIGER KIDS",
        "name": "로고 패디드 자켓",
        "price": "199,750",
        "regular": "235,000",
        "percent": "15%",
        "img": "img/NewIn/Kids/002.jpg",
        "imgSub1":"img/NewIn/Kids/002-1.jpg",
        "category": "키즈",
        "gender":"공용",
        "style":"아우터"
    },
    {
        "id": "NK003",
        "brand": "TOMMY HILFIGER KIDS",
        "name": "힐피거 크레스트 바시티 스웨트팬츠",
        "price": "83,300",
        "regular": "98,000",
        "percent": "15%",
        "img": "img/NewIn/Kids/003.jpg",
        "imgSub1":"img/NewIn/Kids/003-1.jpg",
        "imgSub2":"img/NewIn/Kids/003-2.jpg",
        "imgSub3":"img/NewIn/Kids/003-3.jpg",
        "category": "키즈",
        "gender":"공용",
        "style":"아우터"
    },
    {
        "id": "NK004",
        "brand": "TOMMY HILFIGER WOMEN",
        "name": "힐피거 크레스트 바시티 스웨트팬츠",
        "price": "83,300",
        "regular": "98,000",
        "percent": "15%",
        "img": "img/NewIn/Kids/004.jpg",
        "imgSub1":"img/NewIn/Kids/004-1.jpg",
        "imgSub2":"img/NewIn/Kids/004-2.jpg",
        "imgSub3":"img/NewIn/Kids/004-3.jpg",
        "category": "키즈",
        "gender":"공용",
        "style":"아우터"
    },
    {
        "id": "NK005",
        "brand": "TOMMY HILFIGER KIDS",
        "name": "브러시드 테이퍼드 치노 팬츠",
        "price": "83,300",
        "regular": "98,000",
        "percent": "15%",
        "img": "img/NewIn/Kids/005.jpg",
        "imgSub1":"img/NewIn/Kids/005-1.jpg",
        "imgSub2":"img/NewIn/Kids/005-2.jpg",
        "imgSub3":"img/NewIn/Kids/005-3.jpg",
        "category": "키즈",
        "gender":"공용",
        "style":"아우터"
    },
    {
        "id": "NK006",
        "brand": "TOMMY HILFIGER KIDS",
        "name": "브러시드 테이퍼드 치노 팬츠",
        "price": "83,300",
        "regular": "98,000",
        "percent": "15%",
        "img": "img/NewIn/Kids/006.jpg",
        "imgSub1":"img/NewIn/Kids/006-1.jpg",
        "imgSub2":"img/NewIn/Kids/006-2.jpg",
        "imgSub3":"img/NewIn/Kids/006-3.jpg",
        "category": "키즈",
        "gender":"공용",
        "style":"아우터"
    },
    {
        "id": "NK007",
        "brand": "TOMMY HILFIGER KIDS",
        "name": "에센셜 패디드 파카",
        "price": "267,750",
        "regular": "315,000",
        "percent": "15",
        "img": "img/NewIn/Kids/007.jpg",
        "imgSub1":"img/NewIn/Kids/007-1.jpg",
        "imgSub2":"img/NewIn/Kids/007-2.jpg",
        "imgSub3":"img/NewIn/Kids/007-3.jpg",
        "category": "키즈",
        "gender":"공용",
        "style":"아우터"
    },
    {
        "id": "NK008",
        "brand": "TOMMY HILFIGER KIDS",
        "name": "셰르파 체크 자켓",
        "price": "233,750",
        "regular": "275,000",
        "percent": "15",
        "img": "img/NewIn/Kids/008.jpg",
        "imgSub1":"img/NewIn/Kids/008-1.jpg",
        "imgSub2":"img/NewIn/Kids/008-2.jpg",
        "imgSub3":"img/NewIn/Kids/008-3.jpg",
        "category": "키즈",
        "gender":"공용",
        "style":"아우터"
    },
    {
        "id": "NK009",
        "brand": "TOMMY HILFIGER KIDS",
        "name": "크레스트 스웨터",
        "price": "267,750",
        "regular": "315,000",
        "percent": "15",
        "img": "img/NewIn/Kids/009.jpg",
        "imgSub1":"img/NewIn/Kids/009-1.jpg",
        "imgSub2":"img/NewIn/Kids/009-2.jpg",
        "imgSub3":"img/NewIn/Kids/009-3.jpg",
        "category": "키즈",
        "gender":"공용",
        "style":"아우터"
    },
    {
        "id": "NK010",
        "brand": "TOMMY HILFIGER KIDS",
        "name": "리버시블 셰르파 체크 베스트",
        "price": "165,750",
        "regular": "195,000",
        "percent": "15",
        "img": "img/NewIn/Kids/010.jpg",
        "imgSub1":"img/NewIn/Kids/010-1.jpg",
        "imgSub2":"img/NewIn/Kids/010-2.jpg",
        "imgSub3":"img/NewIn/Kids/010-3.jpg",
        "category": "키즈",
        "gender":"공용",
        "style":"아우터"
    }
]
